verse/interface/api/__init__.py
verse/interface/api/_helper.py
verse/interface/api/_models.py
verse/interface/api/_operation.py
verse/interface/api/component.py
verse/interface/api/exceptions.py
verse/interface/api/providers/default.py
verse/interface/api/providers/fastapi.py
verse/interface/api/py.typed
verse/interface/cli/__init__.py
verse/interface/cli/component.py
verse/interface/cli/providers/default.py
verse/interface/cli/py.typed
verse/interface/web/component.py
verse/interface/web/providers/default.py
verse/interface/web/providers/nextjs.py
verse/interface/worker/__init__.py
verse/interface/worker/_operation.py
verse/interface/worker/component.py
verse/interface/worker/providers/default.py
verse/interface/worker/py.typed
verse_interface-0.0.33.dist-info/LICENSE
verse_interface-0.0.33.dist-info/METADATA
verse_interface-0.0.33.dist-info/WHEEL
verse_interface-0.0.33.dist-info/RECORD
