Metadata-Version: 2.3
Name: verse-interface
Version: 0.0.33
Summary: Verse Inteface Components
License: MIT
Keywords: verse,interface,components
Author: Verse
Author-email: admin@rapidverse.com
Requires-Python: >=3.9
Classifier: License :: OSI Approved :: MIT License
Classifier: Programming Language :: Python :: 3
Classifier: Programming Language :: Python :: 3.9
Classifier: Programming Language :: Python :: 3.10
Classifier: Programming Language :: Python :: 3.11
Classifier: Programming Language :: Python :: 3.12
Classifier: Programming Language :: Python :: 3.13
Provides-Extra: all
Provides-Extra: api-default
Provides-Extra: api-fastapi
Provides-Extra: cli-default
Provides-Extra: worker-default
Requires-Dist: fastapi ; extra == "api-fastapi" or extra == "api-default" or extra == "all"
Requires-Dist: uvicorn ; extra == "api-fastapi" or extra == "api-default" or extra == "all"
Project-URL: Documentation, https://github.com/rapidverse/verse
Project-URL: Homepage, https://github.com/rapidverse/verse
Project-URL: Repository, https://github.com/rapidverse/verse
